ctdmodule/__init__.py
ctdmodule/utilities.py
CTDProcessingPackage-1.7.10.dist-info/METADATA
CTDProcessingPackage-1.7.10.dist-info/WHEEL
CTDProcessingPackage-1.7.10.dist-info/top_level.txt
CTDProcessingPackage-1.7.10.dist-info/RECORD
