Metadata-Version: 2.1
Name: CTDProcessingPackage
Version: 1.7.10
Summary: Package for pre-processing CTD data
Home-page: 
Author: Rafael S. Bittencourt
Author-email: rafael.bittencourt.2002@gmail.com
